willing_zg/__init__.py
willing_zg/apps.py
willing_zg/mailer.py
willing_zg/settings/__init__.py
willing_zg/settings/cookies.py
willing_zg/settings/email.py
willing_zg/settings/jwt.py
willing_zg/settings/secrets.py
willing_zg/templates/email/mlp_transactional_email.html
willing_zg/templates/email/mlp_transactional_email.txt
willing_zg/urls.py
willing_zg/views.py
django_willing_zg-0.9.0.dist-info/METADATA
django_willing_zg-0.9.0.dist-info/WHEEL
django_willing_zg-0.9.0.dist-info/RECORD
