Metadata-Version: 2.1
Name: django-willing-zg
Version: 0.9.0
Summary: 
Author: Bequest, Inc.
Author-email: oss@willing.com
Requires-Python: >=3.8,<4.0
Classifier: Programming Language :: Python :: 3
Classifier: Programming Language :: Python :: 3.8
Classifier: Programming Language :: Python :: 3.9
Classifier: Programming Language :: Python :: 3.10
Classifier: Programming Language :: Python :: 3.11
Requires-Dist: cryptography (>=42.0.2)
Requires-Dist: django (>=4.2.10,<6.0)
Requires-Dist: djangorestframework (>=3.14.0,<4.0.0)
Requires-Dist: djangorestframework-simplejwt (>=5.3.1,<6.0.0)
Requires-Dist: pytest (>=8.0.0,<9.0.0)
Requires-Dist: simplejwt-extensions (>=0.2.1,<0.3.0)
Requires-Dist: zygoat-django (>=1.0.1)
